.coveragerc
.git_archival.txt
.gitattributes
.gitignore
.readthedocs.yaml
CHANGES.rst
LICENSE.rst
README.rst
pyproject.toml
requirements.txt
setup.py
.github/dependabot.yml
.github/workflows/linting.yaml
.github/workflows/test_main_branch.yaml
diffhalos/__init__.py
diffhalos/_version.py
diffhalos/defaults.py
diffhalos.egg-info/PKG-INFO
diffhalos.egg-info/SOURCES.txt
diffhalos.egg-info/dependency_links.txt
diffhalos.egg-info/requires.txt
diffhalos.egg-info/top_level.txt
diffhalos/calibrations/__init__.py
diffhalos/calibrations/ccshmf_cal/__init__.py
diffhalos/calibrations/ccshmf_cal/default_params.py
diffhalos/calibrations/ccshmf_cal/dev_lc_subs.py
diffhalos/calibrations/ccshmf_cal/tests/__init__.py
diffhalos/calibrations/ccshmf_cal/tests/test_default_pararms.py
diffhalos/calibrations/fitting_utils/__init__.py
diffhalos/calibrations/fitting_utils/fitting_helpers.py
diffhalos/calibrations/hmf_cal/__init__.py
diffhalos/calibrations/hmf_cal/hacc_core_hmf_params.py
diffhalos/calibrations/hmf_cal/smdpl_hmf.py
diffhalos/calibrations/hmf_cal/tests/__init__.py
diffhalos/calibrations/hmf_cal/tests/test_hacc_core_hmf_params.py
diffhalos/ccshmf/__init__.py
diffhalos/ccshmf/ccshmf_kernels.py
diffhalos/ccshmf/ccshmf_model.py
diffhalos/ccshmf/mc_subs.py
diffhalos/ccshmf/tests/__init__.py
diffhalos/ccshmf/tests/test_ccshmf_kernels.py
diffhalos/ccshmf/tests/test_ccshmf_model.py
diffhalos/ccshmf/tests/test_mc_subs.py
diffhalos/hmf/__init__.py
diffhalos/hmf/hmf_kernels.py
diffhalos/hmf/hmf_model.py
diffhalos/hmf/mc_hosts.py
diffhalos/hmf/tests/__init__.py
diffhalos/hmf/tests/test_hmf_kernels.py
diffhalos/hmf/tests/test_hmf_model.py
diffhalos/hmf/tests/test_mc_hosts.py
diffhalos/lightcone/__init__.py
diffhalos/lightcone/mc_lightcone_halos.py
diffhalos/lightcone/mc_lightcone_subhalos.py
diffhalos/lightcone/tests/__init__.py
diffhalos/lightcone/tests/test_mc_lightcone_halos.py
diffhalos/lightcone/tests/test_mc_lightcone_subhalos.py
diffhalos/mah/__init__.py
diffhalos/mah/diffmahnet_utils.py
diffhalos/mah/diffmahpop_utils.py
diffhalos/mah/utils.py
diffhalos/mah/diffmahnet/__init__.py
diffhalos/mah/diffmahnet/datatools.py
