Metadata-Version: 2.4
Name: diffhalos
Version: 0.0.4
Summary: Library for differentiable generation of halo lightcones
Author-email: Georgios Zacharegkas <gzacharegkas@anl.gov>, Andrew Hearin <ahearin@anl.gov>
License: BSD 3-Clause License
Project-URL: home, https://github.com/ArgonneCPAC/diffhalos
Classifier: Programming Language :: Python :: 3
Requires-Python: >=3.11
License-File: LICENSE.rst
Requires-Dist: numpy
Requires-Dist: jax
Requires-Dist: dsps
Requires-Dist: diffmah
Requires-Dist: dsps
Requires-Dist: flowjax
Dynamic: license-file
